<?xml version="1.0" encoding="UTF-8"?>
<program><functionDefinitionList><functionDefinition><functionType><type><int attribute="int"></int></type></functionType><functionName><identifier attribute="a"></identifier></functionName><left_bracket_delim></left_bracket_delim><parameterList><parameter><type><int attribute="int"></int></type><variable><identifier attribute="aa"></identifier><arrayOrNothing></arrayOrNothing></variable></parameter><parameterList1></parameterList1></parameterList><right_bracket_delim></right_bracket_delim><block><l_c_bracket_delim></l_c_bracket_delim><statements><statement><simpleStatement><variableDeclaration><type><int attribute="int"></int></type><variable><identifier attribute="a"></identifier><arrayOrNothing></arrayOrNothing></variable><afterVariable></afterVariable></variableDeclaration></simpleStatement></statement><colon_delim></colon_delim><statements1><statement><reservedStatement><return></return><expressionOrNothning><expression><expression1></expression1><orExpression><orExpression1></orExpression1><andExpression><andExpression1></andExpression1><comparisonExpression><comparisonExpression1></comparisonExpression1><term><term1></term1><factor><variableOrFuncCall><afterIdentifier></afterIdentifier><identifier attribute="a"></identifier></variableOrFuncCall></factor></term></comparisonExpression></andExpression></orExpression></expression></expressionOrNothning></reservedStatement></statement><colon_delim></colon_delim><statements1></statements1></statements1></statements><r_c_bracket_delim></r_c_bracket_delim></block></functionDefinition><functionDefinitionList1><functionDefinition><functionType><type><char attribute="char"></char></type></functionType><functionName><identifier attribute="a2"></identifier></functionName><left_bracket_delim></left_bracket_delim><parameterList><parameter><type><int attribute="int"></int></type><variable><identifier attribute="aa"></identifier><arrayOrNothing></arrayOrNothing></variable></parameter><parameterList1></parameterList1></parameterList><right_bracket_delim></right_bracket_delim><block><l_c_bracket_delim></l_c_bracket_delim><statements><statement><simpleStatement><variableDeclaration><type><char attribute="char"></char></type><variable><identifier attribute="a"></identifier><arrayOrNothing></arrayOrNothing></variable><afterVariable></afterVariable></variableDeclaration></simpleStatement></statement><colon_delim></colon_delim><statements1><statement><reservedStatement><return></return><expressionOrNothning><expression><expression1></expression1><orExpression><orExpression1></orExpression1><andExpression><andExpression1></andExpression1><comparisonExpression><comparisonExpression1></comparisonExpression1><term><term1></term1><factor><variableOrFuncCall><afterIdentifier></afterIdentifier><identifier attribute="a"></identifier></variableOrFuncCall></factor></term></comparisonExpression></andExpression></orExpression></expression></expressionOrNothning></reservedStatement></statement><colon_delim></colon_delim><statements1></statements1></statements1></statements><r_c_bracket_delim></r_c_bracket_delim></block></functionDefinition><functionDefinitionList1><functionDefinition><functionType><type><int attribute="int"></int></type></functionType><functionName><identifier attribute="b"></identifier></functionName><left_bracket_delim></left_bracket_delim><parameterList></parameterList><right_bracket_delim></right_bracket_delim><block><l_c_bracket_delim></l_c_bracket_delim><statements><statement><simpleStatement><variableDeclaration><type><int attribute="int"></int></type><variable><identifier attribute="a"></identifier><arrayOrNothing></arrayOrNothing></variable><afterVariable></afterVariable></variableDeclaration></simpleStatement></statement><colon_delim></colon_delim><statements1><statement><reservedStatement><return></return><expressionOrNothning><expression><expression1></expression1><orExpression><orExpression1></orExpression1><andExpression><andExpression1></andExpression1><comparisonExpression><comparisonExpression1></comparisonExpression1><term><term1></term1><factor><variableOrFuncCall><afterIdentifier></afterIdentifier><identifier attribute="a"></identifier></variableOrFuncCall></factor></term></comparisonExpression></andExpression></orExpression></expression></expressionOrNothning></reservedStatement></statement><colon_delim></colon_delim><statements1></statements1></statements1></statements><r_c_bracket_delim></r_c_bracket_delim></block></functionDefinition><functionDefinitionList1><functionDefinition><functionType><type><int attribute="int"></int></type></functionType><functionName><identifier attribute="fibonacci"></identifier></functionName><left_bracket_delim></left_bracket_delim><parameterList><parameter><type><int attribute="int"></int></type><variable><identifier attribute="number"></identifier><arrayOrNothing></arrayOrNothing></variable></parameter><parameterList1></parameterList1></parameterList><right_bracket_delim></right_bracket_delim><block><l_c_bracket_delim></l_c_bracket_delim><statements><statement><controlStatement><ifStatement><if></if><left_bracket_delim></left_bracket_delim><expression><expression1></expression1><orExpression><orExpression1></orExpression1><andExpression><andExpression1><andExpression1></andExpression1><comparisonExpression><comparisonExpression1></comparisonExpression1><term><term1></term1><factor><constant><int_const attribute="0"></int_const></constant></factor></term></comparisonExpression><comparisonOperator><equal_equal_op></equal_equal_op></comparisonOperator></andExpression1><comparisonExpression><comparisonExpression1></comparisonExpression1><term><term1></term1><factor><variableOrFuncCall><afterIdentifier></afterIdentifier><identifier attribute="number"></identifier></variableOrFuncCall></factor></term></comparisonExpression></andExpression></orExpression></expression><right_bracket_delim></right_bracket_delim><block><l_c_bracket_delim></l_c_bracket_delim><statements><statement><reservedStatement><return></return><expressionOrNothning><expression><expression1></expression1><orExpression><orExpression1></orExpression1><andExpression><andExpression1></andExpression1><comparisonExpression><comparisonExpression1></comparisonExpression1><term><term1></term1><factor><constant><int_const attribute="0"></int_const></constant></factor></term></comparisonExpression></andExpression></orExpression></expression></expressionOrNothning></reservedStatement></statement><colon_delim></colon_delim><statements1></statements1></statements><r_c_bracket_delim></r_c_bracket_delim></block><ifStatement1><else></else><block><l_c_bracket_delim></l_c_bracket_delim><statements><statement><controlStatement><ifStatement><if></if><left_bracket_delim></left_bracket_delim><expression><expression1></expression1><orExpression><orExpression1></orExpression1><andExpression><andExpression1><andExpression1></andExpression1><comparisonExpression><comparisonExpression1></comparisonExpression1><term><term1></term1><factor><constant><int_const attribute="1"></int_const></constant></factor></term></comparisonExpression><comparisonOperator><equal_equal_op></equal_equal_op></comparisonOperator></andExpression1><comparisonExpression><comparisonExpression1></comparisonExpression1><term><term1></term1><factor><variableOrFuncCall><afterIdentifier></afterIdentifier><identifier attribute="number"></identifier></variableOrFuncCall></factor></term></comparisonExpression></andExpression></orExpression></expression><right_bracket_delim></right_bracket_delim><block><l_c_bracket_delim></l_c_bracket_delim><statements><statement><reservedStatement><return></return><expressionOrNothning><expression><expression1></expression1><orExpression><orExpression1></orExpression1><andExpression><andExpression1></andExpression1><comparisonExpression><comparisonExpression1></comparisonExpression1><term><term1></term1><factor><constant><int_const attribute="1"></int_const></constant></factor></term></comparisonExpression></andExpression></orExpression></expression></expressionOrNothning></reservedStatement></statement><colon_delim></colon_delim><statements1></statements1></statements><r_c_bracket_delim></r_c_bracket_delim></block><ifStatement1><else></else><block><l_c_bracket_delim></l_c_bracket_delim><statements><statement><reservedStatement><return></return><expressionOrNothning><expression><expression1></expression1><orExpression><orExpression1></orExpression1><andExpression><andExpression1></andExpression1><comparisonExpression><comparisonExpression1><comparisonExpression1></comparisonExpression1><term><term1></term1><factor><variableOrFuncCall><afterIdentifier><functionCall><right_bracket_delim></right_bracket_delim><callVariableList><callVariableList1></callVariableList1><expression><expression1></expression1><orExpression><orExpression1></orExpression1><andExpression><andExpression1></andExpression1><comparisonExpression><comparisonExpression1><comparisonExpression1></comparisonExpression1><term><term1></term1><factor><constant><int_const attribute="2"></int_const></constant></factor></term><addOperator><minus_op></minus_op></addOperator></comparisonExpression1><term><term1></term1><factor><variableOrFuncCall><afterIdentifier></afterIdentifier><identifier attribute="number"></identifier></variableOrFuncCall></factor></term></comparisonExpression></andExpression></orExpression></expression></callVariableList><left_bracket_delim></left_bracket_delim></functionCall></afterIdentifier><identifier attribute="fibonacci"></identifier></variableOrFuncCall></factor></term><addOperator><plus_op></plus_op></addOperator></comparisonExpression1><term><term1></term1><factor><variableOrFuncCall><afterIdentifier><functionCall><right_bracket_delim></right_bracket_delim><callVariableList><callVariableList1></callVariableList1><expression><expression1></expression1><orExpression><orExpression1></orExpression1><andExpression><andExpression1></andExpression1><comparisonExpression><comparisonExpression1><comparisonExpression1></comparisonExpression1><term><term1></term1><factor><constant><int_const attribute="1"></int_const></constant></factor></term><addOperator><minus_op></minus_op></addOperator></comparisonExpression1><term><term1></term1><factor><variableOrFuncCall><afterIdentifier></afterIdentifier><identifier attribute="number"></identifier></variableOrFuncCall></factor></term></comparisonExpression></andExpression></orExpression></expression></callVariableList><left_bracket_delim></left_bracket_delim></functionCall></afterIdentifier><identifier attribute="fibonacci"></identifier></variableOrFuncCall></factor></term></comparisonExpression></andExpression></orExpression></expression></expressionOrNothning></reservedStatement></statement><colon_delim></colon_delim><statements1></statements1></statements><r_c_bracket_delim></r_c_bracket_delim></block></ifStatement1></ifStatement></controlStatement></statement><colon_delim></colon_delim><statements1></statements1></statements><r_c_bracket_delim></r_c_bracket_delim></block></ifStatement1></ifStatement></controlStatement></statement><colon_delim></colon_delim><statements1></statements1></statements><r_c_bracket_delim></r_c_bracket_delim></block></functionDefinition><functionDefinitionList1><functionDefinition><functionType><typeVoid><void></void></typeVoid></functionType><functionName><identifier attribute="g"></identifier></functionName><left_bracket_delim></left_bracket_delim><parameterList><parameter><type><int attribute="int"></int></type><variable><identifier attribute="c"></identifier><arrayOrNothing><arrayVariable><l_s_bracket_delim></l_s_bracket_delim><expressionOrNothning></expressionOrNothning><r_s_bracket_delim></r_s_bracket_delim></arrayVariable></arrayOrNothing></variable></parameter><parameterList1></parameterList1></parameterList><right_bracket_delim></right_bracket_delim><block><l_c_bracket_delim></l_c_bracket_delim><statements><statement><simpleStatement><ioStatement><outputStatement><write></write><left_bracket_delim></left_bracket_delim><expression><expression1></expression1><orExpression><orExpression1></orExpression1><andExpression><andExpression1></andExpression1><comparisonExpression><comparisonExpression1></comparisonExpression1><term><term1></term1><factor><variableOrFuncCall><afterIdentifier><arrayVariable><l_s_bracket_delim></l_s_bracket_delim><expressionOrNothning><expression><expression1></expression1><orExpression><orExpression1></orExpression1><andExpression><andExpression1></andExpression1><comparisonExpression><comparisonExpression1></comparisonExpression1><term><term1></term1><factor><constant><int_const attribute="5"></int_const></constant></factor></term></comparisonExpression></andExpression></orExpression></expression></expressionOrNothning><r_s_bracket_delim></r_s_bracket_delim></arrayVariable></afterIdentifier><identifier attribute="c"></identifier></variableOrFuncCall></factor></term></comparisonExpression></andExpression></orExpression></expression><right_bracket_delim></right_bracket_delim></outputStatement></ioStatement></simpleStatement></statement><colon_delim></colon_delim><statements1><statement><simpleStatement><funcOrAssignment><identifier attribute="c"></identifier><funcOrAssignment1><arrayVariable><l_s_bracket_delim></l_s_bracket_delim><expressionOrNothning><expression><expression1></expression1><orExpression><orExpression1></orExpression1><andExpression><andExpression1></andExpression1><comparisonExpression><comparisonExpression1></comparisonExpression1><term><term1></term1><factor><constant><int_const attribute="5"></int_const></constant></factor></term></comparisonExpression></andExpression></orExpression></expression></expressionOrNothning><r_s_bracket_delim></r_s_bracket_delim></arrayVariable><assignmentStatement><assignmentOp><equal_op></equal_op></assignmentOp><assignOrIncDec1><expression><expression1></expression1><orExpression><orExpression1></orExpression1><andExpression><andExpression1></andExpression1><comparisonExpression><comparisonExpression1></comparisonExpression1><term><term1></term1><factor><constant><int_const attribute="4444"></int_const></constant></factor></term></comparisonExpression></andExpression></orExpression></expression></assignOrIncDec1></assignmentStatement></funcOrAssignment1></funcOrAssignment></simpleStatement></statement><colon_delim></colon_delim><statements1><statement><simpleStatement><funcOrAssignment><identifier attribute="c"></identifier><funcOrAssignment1><arrayVariable><l_s_bracket_delim></l_s_bracket_delim><expressionOrNothning><expression><expression1></expression1><orExpression><orExpression1></orExpression1><andExpression><andExpression1></andExpression1><comparisonExpression><comparisonExpression1></comparisonExpression1><term><term1></term1><factor><constant><int_const attribute="3"></int_const></constant></factor></term></comparisonExpression></andExpression></orExpression></expression></expressionOrNothning><r_s_bracket_delim></r_s_bracket_delim></arrayVariable><assignmentStatement><assignmentOp><equal_op></equal_op></assignmentOp><assignOrIncDec1><expression><expression1></expression1><orExpression><orExpression1></orExpression1><andExpression><andExpression1></andExpression1><comparisonExpression><comparisonExpression1></comparisonExpression1><term><term1></term1><factor><constant><int_const attribute="5555"></int_const></constant></factor></term></comparisonExpression></andExpression></orExpression></expression></assignOrIncDec1></assignmentStatement></funcOrAssignment1></funcOrAssignment></simpleStatement></statement><colon_delim></colon_delim><statements1></statements1></statements1></statements1></statements><r_c_bracket_delim></r_c_bracket_delim></block></functionDefinition><functionDefinitionList1><functionDefinition><functionType><typeVoid><void></void></typeVoid></functionType><functionName><identifier attribute="f"></identifier></functionName><left_bracket_delim></left_bracket_delim><parameterList><parameter><type><int attribute="int"></int></type><variable><identifier attribute="b"></identifier><arrayOrNothing><arrayVariable><l_s_bracket_delim></l_s_bracket_delim><expressionOrNothning></expressionOrNothning><r_s_bracket_delim></r_s_bracket_delim></arrayVariable></arrayOrNothing></variable></parameter><parameterList1></parameterList1></parameterList><right_bracket_delim></right_bracket_delim><block><l_c_bracket_delim></l_c_bracket_delim><statements><statement><simpleStatement><ioStatement><outputStatement><write></write><left_bracket_delim></left_bracket_delim><expression><expression1></expression1><orExpression><orExpression1></orExpression1><andExpression><andExpression1></andExpression1><comparisonExpression><comparisonExpression1></comparisonExpression1><term><term1></term1><factor><variableOrFuncCall><afterIdentifier><arrayVariable><l_s_bracket_delim></l_s_bracket_delim><expressionOrNothning><expression><expression1></expression1><orExpression><orExpression1></orExpression1><andExpression><andExpression1></andExpression1><comparisonExpression><comparisonExpression1></comparisonExpression1><term><term1></term1><factor><constant><int_const attribute="5"></int_const></constant></factor></term></comparisonExpression></andExpression></orExpression></expression></expressionOrNothning><r_s_bracket_delim></r_s_bracket_delim></arrayVariable></afterIdentifier><identifier attribute="b"></identifier></variableOrFuncCall></factor></term></comparisonExpression></andExpression></orExpression></expression><right_bracket_delim></right_bracket_delim></outputStatement></ioStatement></simpleStatement></statement><colon_delim></colon_delim><statements1><statement><simpleStatement><funcOrAssignment><identifier attribute="b"></identifier><funcOrAssignment1><arrayVariable><l_s_bracket_delim></l_s_bracket_delim><expressionOrNothning><expression><expression1></expression1><orExpression><orExpression1></orExpression1><andExpression><andExpression1></andExpression1><comparisonExpression><comparisonExpression1></comparisonExpression1><term><term1></term1><factor><constant><int_const attribute="5"></int_const></constant></factor></term></comparisonExpression></andExpression></orExpression></expression></expressionOrNothning><r_s_bracket_delim></r_s_bracket_delim></arrayVariable><assignmentStatement><assignmentOp><equal_op></equal_op></assignmentOp><assignOrIncDec1><expression><expression1></expression1><orExpression><orExpression1></orExpression1><andExpression><andExpression1></andExpression1><comparisonExpression><comparisonExpression1></comparisonExpression1><term><term1></term1><factor><constant><int_const attribute="1111"></int_const></constant></factor></term></comparisonExpression></andExpression></orExpression></expression></assignOrIncDec1></assignmentStatement></funcOrAssignment1></funcOrAssignment></simpleStatement></statement><colon_delim></colon_delim><statements1><statement><simpleStatement><funcOrAssignment><identifier attribute="g"></identifier><funcOrAssignment1><functionCall><right_bracket_delim></right_bracket_delim><callVariableList><callVariableList1></callVariableList1><expression><expression1></expression1><orExpression><orExpression1></orExpression1><andExpression><andExpression1></andExpression1><comparisonExpression><comparisonExpression1></comparisonExpression1><term><term1></term1><factor><variableOrFuncCall><afterIdentifier><arrayVariable><l_s_bracket_delim></l_s_bracket_delim><expressionOrNothning></expressionOrNothning><r_s_bracket_delim></r_s_bracket_delim></arrayVariable></afterIdentifier><identifier attribute="b"></identifier></variableOrFuncCall></factor></term></comparisonExpression></andExpression></orExpression></expression></callVariableList><left_bracket_delim></left_bracket_delim></functionCall></funcOrAssignment1></funcOrAssignment></simpleStatement></statement><colon_delim></colon_delim><statements1></statements1></statements1></statements1></statements><r_c_bracket_delim></r_c_bracket_delim></block></functionDefinition><functionDefinitionList1><functionDefinition><functionType><type><int attribute="int"></int></type></functionType><functionName><identifier attribute="fib"></identifier></functionName><left_bracket_delim></left_bracket_delim><parameterList><parameter><type><int attribute="int"></int></type><variable><identifier attribute="number"></identifier><arrayOrNothing></arrayOrNothing></variable></parameter><parameterList1></parameterList1></parameterList><right_bracket_delim></right_bracket_delim><block><l_c_bracket_delim></l_c_bracket_delim><statements><statement><simpleStatement><variableDeclaration><type><int attribute="int"></int></type><variable><identifier attribute="tmp"></identifier><arrayOrNothing><arrayVariable><l_s_bracket_delim></l_s_bracket_delim><expressionOrNothning><expression><expression1></expression1><orExpression><orExpression1></orExpression1><andExpression><andExpression1></andExpression1><comparisonExpression><comparisonExpression1><comparisonExpression1></comparisonExpression1><term><term1></term1><factor><constant><int_const attribute="1"></int_const></constant></factor></term><addOperator><plus_op></plus_op></addOperator></comparisonExpression1><term><term1></term1><factor><variableOrFuncCall><afterIdentifier></afterIdentifier><identifier attribute="number"></identifier></variableOrFuncCall></factor></term></comparisonExpression></andExpression></orExpression></expression></expressionOrNothning><r_s_bracket_delim></r_s_bracket_delim></arrayVariable></arrayOrNothing></variable><afterVariable></afterVariable></variableDeclaration></simpleStatement></statement><colon_delim></colon_delim><statements1><statement><simpleStatement><funcOrAssignment><identifier attribute="tmp"></identifier><funcOrAssignment1><arrayVariable><l_s_bracket_delim></l_s_bracket_delim><expressionOrNothning><expression><expression1></expression1><orExpression><orExpression1></orExpression1><andExpression><andExpression1></andExpression1><comparisonExpression><comparisonExpression1></comparisonExpression1><term><term1></term1><factor><constant><int_const attribute="0"></int_const></constant></factor></term></comparisonExpression></andExpression></orExpression></expression></expressionOrNothning><r_s_bracket_delim></r_s_bracket_delim></arrayVariable><assignmentStatement><assignmentOp><equal_op></equal_op></assignmentOp><assignOrIncDec1><expression><expression1></expression1><orExpression><orExpression1></orExpression1><andExpression><andExpression1></andExpression1><comparisonExpression><comparisonExpression1></comparisonExpression1><term><term1></term1><factor><constant><int_const attribute="0"></int_const></constant></factor></term></comparisonExpression></andExpression></orExpression></expression></assignOrIncDec1></assignmentStatement></funcOrAssignment1></funcOrAssignment></simpleStatement></statement><colon_delim></colon_delim><statements1><statement><simpleStatement><funcOrAssignment><identifier attribute="tmp"></identifier><funcOrAssignment1><arrayVariable><l_s_bracket_delim></l_s_bracket_delim><expressionOrNothning><expression><expression1></expression1><orExpression><orExpression1></orExpression1><andExpression><andExpression1></andExpression1><comparisonExpression><comparisonExpression1></comparisonExpression1><term><term1></term1><factor><constant><int_const attribute="1"></int_const></constant></factor></term></comparisonExpression></andExpression></orExpression></expression></expressionOrNothning><r_s_bracket_delim></r_s_bracket_delim></arrayVariable><assignmentStatement><assignmentOp><equal_op></equal_op></assignmentOp><assignOrIncDec1><expression><expression1></expression1><orExpression><orExpression1></orExpression1><andExpression><andExpression1></andExpression1><comparisonExpression><comparisonExpression1></comparisonExpression1><term><term1></term1><factor><constant><int_const attribute="1"></int_const></constant></factor></term></comparisonExpression></andExpression></orExpression></expression></assignOrIncDec1></assignmentStatement></funcOrAssignment1></funcOrAssignment></simpleStatement></statement><colon_delim></colon_delim><statements1><statement><simpleStatement><variableDeclaration><type><int attribute="int"></int></type><variable><identifier attribute="i"></identifier><arrayOrNothing></arrayOrNothing></variable><afterVariable></afterVariable></variableDeclaration></simpleStatement></statement><colon_delim></colon_delim><statements1><statement><controlStatement><forLoop><for></for><left_bracket_delim></left_bracket_delim><variable><identifier attribute="i"></identifier><arrayOrNothing></arrayOrNothing></variable><assignmentOp><equal_op></equal_op></assignmentOp><expression><expression1></expression1><orExpression><orExpression1></orExpression1><andExpression><andExpression1></andExpression1><comparisonExpression><comparisonExpression1></comparisonExpression1><term><term1></term1><factor><constant><int_const attribute="2"></int_const></constant></factor></term></comparisonExpression></andExpression></orExpression></expression><to></to><expression><expression1></expression1><orExpression><orExpression1></orExpression1><andExpression><andExpression1></andExpression1><comparisonExpression><comparisonExpression1></comparisonExpression1><term><term1></term1><factor><variableOrFuncCall><afterIdentifier></afterIdentifier><identifier attribute="number"></identifier></variableOrFuncCall></factor></term></comparisonExpression></andExpression></orExpression></expression><right_bracket_delim></right_bracket_delim><block><l_c_bracket_delim></l_c_bracket_delim><statements><statement><simpleStatement><funcOrAssignment><identifier attribute="tmp"></identifier><funcOrAssignment1><arrayVariable><l_s_bracket_delim></l_s_bracket_delim><expressionOrNothning><expression><expression1></expression1><orExpression><orExpression1></orExpression1><andExpression><andExpression1></andExpression1><comparisonExpression><comparisonExpression1></comparisonExpression1><term><term1></term1><factor><variableOrFuncCall><afterIdentifier></afterIdentifier><identifier attribute="i"></identifier></variableOrFuncCall></factor></term></comparisonExpression></andExpression></orExpression></expression></expressionOrNothning><r_s_bracket_delim></r_s_bracket_delim></arrayVariable><assignmentStatement><assignmentOp><equal_op></equal_op></assignmentOp><assignOrIncDec1><expression><expression1></expression1><orExpression><orExpression1></orExpression1><andExpression><andExpression1></andExpression1><comparisonExpression><comparisonExpression1><comparisonExpression1></comparisonExpression1><term><term1></term1><factor><variableOrFuncCall><afterIdentifier><arrayVariable><l_s_bracket_delim></l_s_bracket_delim><expressionOrNothning><expression><expression1></expression1><orExpression><orExpression1></orExpression1><andExpression><andExpression1></andExpression1><comparisonExpression><comparisonExpression1><comparisonExpression1></comparisonExpression1><term><term1></term1><factor><constant><int_const attribute="1"></int_const></constant></factor></term><addOperator><minus_op></minus_op></addOperator></comparisonExpression1><term><term1></term1><factor><variableOrFuncCall><afterIdentifier></afterIdentifier><identifier attribute="i"></identifier></variableOrFuncCall></factor></term></comparisonExpression></andExpression></orExpression></expression></expressionOrNothning><r_s_bracket_delim></r_s_bracket_delim></arrayVariable></afterIdentifier><identifier attribute="tmp"></identifier></variableOrFuncCall></factor></term><addOperator><plus_op></plus_op></addOperator></comparisonExpression1><term><term1></term1><factor><variableOrFuncCall><afterIdentifier><arrayVariable><l_s_bracket_delim></l_s_bracket_delim><expressionOrNothning><expression><expression1></expression1><orExpression><orExpression1></orExpression1><andExpression><andExpression1></andExpression1><comparisonExpression><comparisonExpression1><comparisonExpression1></comparisonExpression1><term><term1></term1><factor><constant><int_const attribute="2"></int_const></constant></factor></term><addOperator><minus_op></minus_op></addOperator></comparisonExpression1><term><term1></term1><factor><variableOrFuncCall><afterIdentifier></afterIdentifier><identifier attribute="i"></identifier></variableOrFuncCall></factor></term></comparisonExpression></andExpression></orExpression></expression></expressionOrNothning><r_s_bracket_delim></r_s_bracket_delim></arrayVariable></afterIdentifier><identifier attribute="tmp"></identifier></variableOrFuncCall></factor></term></comparisonExpression></andExpression></orExpression></expression></assignOrIncDec1></assignmentStatement></funcOrAssignment1></funcOrAssignment></simpleStatement></statement><colon_delim></colon_delim><statements1></statements1></statements><r_c_bracket_delim></r_c_bracket_delim></block></forLoop></controlStatement></statement><colon_delim></colon_delim><statements1><statement><reservedStatement><return></return><expressionOrNothning><expression><expression1></expression1><orExpression><orExpression1></orExpression1><andExpression><andExpression1></andExpression1><comparisonExpression><comparisonExpression1></comparisonExpression1><term><term1></term1><factor><variableOrFuncCall><afterIdentifier><arrayVariable><l_s_bracket_delim></l_s_bracket_delim><expressionOrNothning><expression><expression1></expression1><orExpression><orExpression1></orExpression1><andExpression><andExpression1></andExpression1><comparisonExpression><comparisonExpression1></comparisonExpression1><term><term1></term1><factor><variableOrFuncCall><afterIdentifier></afterIdentifier><identifier attribute="number"></identifier></variableOrFuncCall></factor></term></comparisonExpression></andExpression></orExpression></expression></expressionOrNothning><r_s_bracket_delim></r_s_bracket_delim></arrayVariable></afterIdentifier><identifier attribute="tmp"></identifier></variableOrFuncCall></factor></term></comparisonExpression></andExpression></orExpression></expression></expressionOrNothning></reservedStatement></statement><colon_delim></colon_delim><statements1></statements1></statements1></statements1></statements1></statements1></statements1></statements><r_c_bracket_delim></r_c_bracket_delim></block></functionDefinition><functionDefinitionList1><functionDefinition><functionType><type><int attribute="int"></int></type></functionType><functionName><identifier attribute="fun"></identifier></functionName><left_bracket_delim></left_bracket_delim><parameterList><parameter><type><int attribute="int"></int></type><variable><identifier attribute="param"></identifier><arrayOrNothing></arrayOrNothing></variable></parameter><parameterList1></parameterList1></parameterList><right_bracket_delim></right_bracket_delim><block><l_c_bracket_delim></l_c_bracket_delim><statements><statement><reservedStatement><return></return><expressionOrNothning><expression><expression1></expression1><orExpression><orExpression1></orExpression1><andExpression><andExpression1></andExpression1><comparisonExpression><comparisonExpression1></comparisonExpression1><term><term1><term1></term1><factor><constant><int_const attribute="2"></int_const></constant></factor><mulOperator><mul_op></mul_op></mulOperator></term1><factor><variableOrFuncCall><afterIdentifier></afterIdentifier><identifier attribute="param"></identifier></variableOrFuncCall></factor></term></comparisonExpression></andExpression></orExpression></expression></expressionOrNothning></reservedStatement></statement><colon_delim></colon_delim><statements1></statements1></statements><r_c_bracket_delim></r_c_bracket_delim></block></functionDefinition><functionDefinitionList1><functionDefinition><functionType><type><int attribute="int"></int></type></functionType><functionName><identifier attribute="factorial"></identifier></functionName><left_bracket_delim></left_bracket_delim><parameterList><parameter><type><int attribute="int"></int></type><variable><identifier attribute="number"></identifier><arrayOrNothing></arrayOrNothing></variable></parameter><parameterList1></parameterList1></parameterList><right_bracket_delim></right_bracket_delim><block><l_c_bracket_delim></l_c_bracket_delim><statements><statement><controlStatement><ifStatement><if></if><left_bracket_delim></left_bracket_delim><expression><expression1></expression1><orExpression><orExpression1></orExpression1><andExpression><andExpression1><andExpression1></andExpression1><comparisonExpression><comparisonExpression1></comparisonExpression1><term><term1></term1><factor><constant><int_const attribute="0"></int_const></constant></factor></term></comparisonExpression><comparisonOperator><equal_equal_op></equal_equal_op></comparisonOperator></andExpression1><comparisonExpression><comparisonExpression1></comparisonExpression1><term><term1></term1><factor><variableOrFuncCall><afterIdentifier></afterIdentifier><identifier attribute="number"></identifier></variableOrFuncCall></factor></term></comparisonExpression></andExpression></orExpression></expression><right_bracket_delim></right_bracket_delim><block><l_c_bracket_delim></l_c_bracket_delim><statements><statement><reservedStatement><return></return><expressionOrNothning><expression><expression1></expression1><orExpression><orExpression1></orExpression1><andExpression><andExpression1></andExpression1><comparisonExpression><comparisonExpression1></comparisonExpression1><term><term1></term1><factor><constant><int_const attribute="1"></int_const></constant></factor></term></comparisonExpression></andExpression></orExpression></expression></expressionOrNothning></reservedStatement></statement><colon_delim></colon_delim><statements1></statements1></statements><r_c_bracket_delim></r_c_bracket_delim></block><ifStatement1><else></else><block><l_c_bracket_delim></l_c_bracket_delim><statements><statement><reservedStatement><return></return><expressionOrNothning><expression><expression1></expression1><orExpression><orExpression1></orExpression1><andExpression><andExpression1></andExpression1><comparisonExpression><comparisonExpression1></comparisonExpression1><term><term1><term1></term1><factor><variableOrFuncCall><afterIdentifier></afterIdentifier><identifier attribute="number"></identifier></variableOrFuncCall></factor><mulOperator><mul_op></mul_op></mulOperator></term1><factor><variableOrFuncCall><afterIdentifier><functionCall><right_bracket_delim></right_bracket_delim><callVariableList><callVariableList1></callVariableList1><expression><expression1></expression1><orExpression><orExpression1></orExpression1><andExpression><andExpression1></andExpression1><comparisonExpression><comparisonExpression1><comparisonExpression1></comparisonExpression1><term><term1></term1><factor><constant><int_const attribute="1"></int_const></constant></factor></term><addOperator><minus_op></minus_op></addOperator></comparisonExpression1><term><term1></term1><factor><variableOrFuncCall><afterIdentifier></afterIdentifier><identifier attribute="number"></identifier></variableOrFuncCall></factor></term></comparisonExpression></andExpression></orExpression></expression></callVariableList><left_bracket_delim></left_bracket_delim></functionCall></afterIdentifier><identifier attribute="factorial"></identifier></variableOrFuncCall></factor></term></comparisonExpression></andExpression></orExpression></expression></expressionOrNothning></reservedStatement></statement><colon_delim></colon_delim><statements1></statements1></statements><r_c_bracket_delim></r_c_bracket_delim></block></ifStatement1></ifStatement></controlStatement></statement><colon_delim></colon_delim><statements1></statements1></statements><r_c_bracket_delim></r_c_bracket_delim></block></functionDefinition><functionDefinitionList1></functionDefinitionList1></functionDefinitionList1></functionDefinitionList1></functionDefinitionList1></functionDefinitionList1></functionDefinitionList1></functionDefinitionList1></functionDefinitionList1></functionDefinitionList1></functionDefinitionList><mainFunction><main></main><block><l_c_bracket_delim></l_c_bracket_delim><statements><statement><simpleStatement><ioStatement><outputStatement><write></write><left_bracket_delim></left_bracket_delim><expression><expression1></expression1><orExpression><orExpression1></orExpression1><andExpression><andExpression1></andExpression1><comparisonExpression><comparisonExpression1></comparisonExpression1><term><term1></term1><factor><variableOrFuncCall><afterIdentifier><functionCall><right_bracket_delim></right_bracket_delim><callVariableList><callVariableList1></callVariableList1><expression><expression1></expression1><orExpression><orExpression1></orExpression1><andExpression><andExpression1></andExpression1><comparisonExpression><comparisonExpression1></comparisonExpression1><term><term1></term1><factor><constant><int_const attribute="10"></int_const></constant></factor></term></comparisonExpression></andExpression></orExpression></expression></callVariableList><left_bracket_delim></left_bracket_delim></functionCall></afterIdentifier><identifier attribute="factorial"></identifier></variableOrFuncCall></factor></term></comparisonExpression></andExpression></orExpression></expression><right_bracket_delim></right_bracket_delim></outputStatement></ioStatement></simpleStatement></statement><colon_delim></colon_delim><statements1><statement><simpleStatement><ioStatement><outputStatement><write></write><left_bracket_delim></left_bracket_delim><expression><expression1></expression1><orExpression><orExpression1></orExpression1><andExpression><andExpression1></andExpression1><comparisonExpression><comparisonExpression1></comparisonExpression1><term><term1></term1><factor><variableOrFuncCall><afterIdentifier><functionCall><right_bracket_delim></right_bracket_delim><callVariableList><callVariableList1></callVariableList1><expression><expression1></expression1><orExpression><orExpression1></orExpression1><andExpression><andExpression1></andExpression1><comparisonExpression><comparisonExpression1></comparisonExpression1><term><term1></term1><factor><constant><int_const attribute="33333"></int_const></constant></factor></term></comparisonExpression></andExpression></orExpression></expression></callVariableList><left_bracket_delim></left_bracket_delim></functionCall></afterIdentifier><identifier attribute="fun"></identifier></variableOrFuncCall></factor></term></comparisonExpression></andExpression></orExpression></expression><right_bracket_delim></right_bracket_delim></outputStatement></ioStatement></simpleStatement></statement><colon_delim></colon_delim><statements1><statement><simpleStatement><variableDeclaration><type><int attribute="int"></int></type><variable><identifier attribute="aaa"></identifier><arrayOrNothing></arrayOrNothing></variable><afterVariable></afterVariable></variableDeclaration></simpleStatement></statement><colon_delim></colon_delim><statements1><statement><simpleStatement><variableDeclaration><type><int attribute="int"></int></type><variable><identifier attribute="bbb"></identifier><arrayOrNothing></arrayOrNothing></variable><afterVariable></afterVariable></variableDeclaration></simpleStatement></statement><colon_delim></colon_delim><statements1><statement><simpleStatement><variableDeclaration><type><int attribute="int"></int></type><variable><identifier attribute="ccc"></identifier><arrayOrNothing></arrayOrNothing></variable><afterVariable></afterVariable></variableDeclaration></simpleStatement></statement><colon_delim></colon_delim><statements1><statement><simpleStatement><ioStatement><outputStatement><write></write><left_bracket_delim></left_bracket_delim><expression><expression1></expression1><orExpression><orExpression1></orExpression1><andExpression><andExpression1></andExpression1><comparisonExpression><comparisonExpression1><comparisonExpression1></comparisonExpression1><term><term1></term1><factor><constant><int_const attribute="5"></int_const></constant></factor></term><addOperator><plus_op></plus_op></addOperator></comparisonExpression1><term><term1><term1><term1></term1><factor><constant><int_const attribute="4"></int_const></constant></factor><mulOperator><mul_op></mul_op></mulOperator></term1><factor><constant><int_const attribute="3"></int_const></constant></factor><mulOperator><mul_op></mul_op></mulOperator></term1><factor><constant><int_const attribute="2"></int_const></constant></factor></term></comparisonExpression></andExpression></orExpression></expression><right_bracket_delim></right_bracket_delim></outputStatement></ioStatement></simpleStatement></statement><colon_delim></colon_delim><statements1><statement><simpleStatement><variableDeclaration><type><int attribute="int"></int></type><variable><identifier attribute="ar"></identifier><arrayOrNothing><arrayVariable><l_s_bracket_delim></l_s_bracket_delim><expressionOrNothning><expression><expression1></expression1><orExpression><orExpression1></orExpression1><andExpression><andExpression1></andExpression1><comparisonExpression><comparisonExpression1></comparisonExpression1><term><term1></term1><factor><constant><int_const attribute="10"></int_const></constant></factor></term></comparisonExpression></andExpression></orExpression></expression></expressionOrNothning><r_s_bracket_delim></r_s_bracket_delim></arrayVariable></arrayOrNothing></variable><afterVariable></afterVariable></variableDeclaration></simpleStatement></statement><colon_delim></colon_delim><statements1><statement><simpleStatement><funcOrAssignment><identifier attribute="ar"></identifier><funcOrAssignment1><arrayVariable><l_s_bracket_delim></l_s_bracket_delim><expressionOrNothning><expression><expression1></expression1><orExpression><orExpression1></orExpression1><andExpression><andExpression1></andExpression1><comparisonExpression><comparisonExpression1></comparisonExpression1><term><term1></term1><factor><constant><int_const attribute="5"></int_const></constant></factor></term></comparisonExpression></andExpression></orExpression></expression></expressionOrNothning><r_s_bracket_delim></r_s_bracket_delim></arrayVariable><assignmentStatement><assignmentOp><equal_op></equal_op></assignmentOp><assignOrIncDec1><expression><expression1></expression1><orExpression><orExpression1></orExpression1><andExpression><andExpression1></andExpression1><comparisonExpression><comparisonExpression1></comparisonExpression1><term><term1></term1><factor><constant><int_const attribute="2222"></int_const></constant></factor></term></comparisonExpression></andExpression></orExpression></expression></assignOrIncDec1></assignmentStatement></funcOrAssignment1></funcOrAssignment></simpleStatement></statement><colon_delim></colon_delim><statements1><statement><simpleStatement><funcOrAssignment><identifier attribute="f"></identifier><funcOrAssignment1><functionCall><right_bracket_delim></right_bracket_delim><callVariableList><callVariableList1></callVariableList1><expression><expression1></expression1><orExpression><orExpression1></orExpression1><andExpression><andExpression1></andExpression1><comparisonExpression><comparisonExpression1></comparisonExpression1><term><term1></term1><factor><variableOrFuncCall><afterIdentifier><arrayVariable><l_s_bracket_delim></l_s_bracket_delim><expressionOrNothning></expressionOrNothning><r_s_bracket_delim></r_s_bracket_delim></arrayVariable></afterIdentifier><identifier attribute="ar"></identifier></variableOrFuncCall></factor></term></comparisonExpression></andExpression></orExpression></expression></callVariableList><left_bracket_delim></left_bracket_delim></functionCall></funcOrAssignment1></funcOrAssignment></simpleStatement></statement><colon_delim></colon_delim><statements1><statement><controlStatement><forLoop><for></for><left_bracket_delim></left_bracket_delim><variable><identifier attribute="aaa"></identifier><arrayOrNothing></arrayOrNothing></variable><assignmentOp><equal_op></equal_op></assignmentOp><expression><expression1></expression1><orExpression><orExpression1></orExpression1><andExpression><andExpression1></andExpression1><comparisonExpression><comparisonExpression1></comparisonExpression1><term><term1></term1><factor><constant><int_const attribute="0"></int_const></constant></factor></term></comparisonExpression></andExpression></orExpression></expression><to></to><expression><expression1></expression1><orExpression><orExpression1></orExpression1><andExpression><andExpression1></andExpression1><comparisonExpression><comparisonExpression1></comparisonExpression1><term><term1></term1><factor><constant><int_const attribute="9"></int_const></constant></factor></term></comparisonExpression></andExpression></orExpression></expression><right_bracket_delim></right_bracket_delim><block><l_c_bracket_delim></l_c_bracket_delim><statements><statement><simpleStatement><ioStatement><outputStatement><write></write><left_bracket_delim></left_bracket_delim><expression><expression1></expression1><orExpression><orExpression1></orExpression1><andExpression><andExpression1></andExpression1><comparisonExpression><comparisonExpression1></comparisonExpression1><term><term1></term1><factor><variableOrFuncCall><afterIdentifier><arrayVariable><l_s_bracket_delim></l_s_bracket_delim><expressionOrNothning><expression><expression1></expression1><orExpression><orExpression1></orExpression1><andExpression><andExpression1></andExpression1><comparisonExpression><comparisonExpression1></comparisonExpression1><term><term1></term1><factor><variableOrFuncCall><afterIdentifier></afterIdentifier><identifier attribute="aaa"></identifier></variableOrFuncCall></factor></term></comparisonExpression></andExpression></orExpression></expression></expressionOrNothning><r_s_bracket_delim></r_s_bracket_delim></arrayVariable></afterIdentifier><identifier attribute="ar"></identifier></variableOrFuncCall></factor></term></comparisonExpression></andExpression></orExpression></expression><right_bracket_delim></right_bracket_delim></outputStatement></ioStatement></simpleStatement></statement><colon_delim></colon_delim><statements1></statements1></statements><r_c_bracket_delim></r_c_bracket_delim></block></forLoop></controlStatement></statement><colon_delim></colon_delim><statements1><statement><simpleStatement><funcOrAssignment><identifier attribute="fib"></identifier><funcOrAssignment1><functionCall><right_bracket_delim></right_bracket_delim><callVariableList><callVariableList1></callVariableList1><expression><expression1></expression1><orExpression><orExpression1></orExpression1><andExpression><andExpression1></andExpression1><comparisonExpression><comparisonExpression1></comparisonExpression1><term><term1></term1><factor><constant><int_const attribute="5"></int_const></constant></factor></term></comparisonExpression></andExpression></orExpression></expression></callVariableList><left_bracket_delim></left_bracket_delim></functionCall></funcOrAssignment1></funcOrAssignment></simpleStatement></statement><colon_delim></colon_delim><statements1><statement><simpleStatement><variableDeclaration><type><float attribute="float"></float></type><variable><identifier attribute="a"></identifier><arrayOrNothing></arrayOrNothing></variable><afterVariable></afterVariable></variableDeclaration></simpleStatement></statement><colon_delim></colon_delim><statements1><statement><simpleStatement><funcOrAssignment><identifier attribute="a"></identifier><funcOrAssignment1><assignmentStatement><assignmentOp><equal_op></equal_op></assignmentOp><assignOrIncDec1><expression><expression1></expression1><orExpression><orExpression1></orExpression1><andExpression><andExpression1></andExpression1><comparisonExpression><comparisonExpression1></comparisonExpression1><term><term1></term1><factor><constant><float_const attribute="3.0"></float_const></constant></factor></term></comparisonExpression></andExpression></orExpression></expression></assignOrIncDec1></assignmentStatement></funcOrAssignment1></funcOrAssignment></simpleStatement></statement><colon_delim></colon_delim><statements1><statement><simpleStatement><variableDeclaration><type><int attribute="int"></int></type><variable><identifier attribute="c"></identifier><arrayOrNothing></arrayOrNothing></variable><afterVariable></afterVariable></variableDeclaration></simpleStatement></statement><colon_delim></colon_delim><statements1><statement><simpleStatement><funcOrAssignment><identifier attribute="c"></identifier><funcOrAssignment1><assignmentStatement><assignmentOp><equal_op></equal_op></assignmentOp><assignOrIncDec1><expression><expression1></expression1><orExpression><orExpression1></orExpression1><andExpression><andExpression1></andExpression1><comparisonExpression><comparisonExpression1></comparisonExpression1><term><term1></term1><factor><constant><int_const attribute="5"></int_const></constant></factor></term></comparisonExpression></andExpression></orExpression></expression></assignOrIncDec1></assignmentStatement></funcOrAssignment1></funcOrAssignment></simpleStatement></statement><colon_delim></colon_delim><statements1><statement><simpleStatement><ioStatement><outputStatement><write></write><left_bracket_delim></left_bracket_delim><expression><expression1></expression1><orExpression><orExpression1></orExpression1><andExpression><andExpression1></andExpression1><comparisonExpression><comparisonExpression1><comparisonExpression1></comparisonExpression1><term><term1><term1></term1><factor><constant><int_const attribute="2"></int_const></constant></factor><mulOperator><mul_op></mul_op></mulOperator></term1><factor><variableOrFuncCall><afterIdentifier></afterIdentifier><identifier attribute="c"></identifier></variableOrFuncCall></factor></term><addOperator><plus_op></plus_op></addOperator></comparisonExpression1><term><term1></term1><factor><variableOrFuncCall><afterIdentifier></afterIdentifier><identifier attribute="a"></identifier></variableOrFuncCall></factor></term></comparisonExpression></andExpression></orExpression></expression><right_bracket_delim></right_bracket_delim></outputStatement></ioStatement></simpleStatement></statement><colon_delim></colon_delim><statements1><statement><simpleStatement><ioStatement><outputStatement><write></write><left_bracket_delim></left_bracket_delim><expression><expression1></expression1><orExpression><orExpression1></orExpression1><andExpression><andExpression1></andExpression1><comparisonExpression><comparisonExpression1></comparisonExpression1><term><term1></term1><factor><variableOrFuncCall><afterIdentifier><functionCall><right_bracket_delim></right_bracket_delim><callVariableList><callVariableList1></callVariableList1><expression><expression1></expression1><orExpression><orExpression1></orExpression1><andExpression><andExpression1></andExpression1><comparisonExpression><comparisonExpression1></comparisonExpression1><term><term1></term1><factor><constant><int_const attribute="6"></int_const></constant></factor></term></comparisonExpression></andExpression></orExpression></expression></callVariableList><left_bracket_delim></left_bracket_delim></functionCall></afterIdentifier><identifier attribute="fib"></identifier></variableOrFuncCall></factor></term></comparisonExpression></andExpression></orExpression></expression><right_bracket_delim></right_bracket_delim></outputStatement></ioStatement></simpleStatement></statement><colon_delim></colon_delim><statements1><statement><simpleStatement><funcOrAssignment><identifier attribute="c"></identifier><funcOrAssignment1><assignmentStatement><assignmentOp><equal_op></equal_op></assignmentOp><assignOrIncDec1><expression><expression1></expression1><orExpression><orExpression1></orExpression1><andExpression><andExpression1></andExpression1><comparisonExpression><comparisonExpression1></comparisonExpression1><term><term1></term1><factor><constant><int_const attribute="22"></int_const></constant></factor></term></comparisonExpression></andExpression></orExpression></expression></assignOrIncDec1></assignmentStatement></funcOrAssignment1></funcOrAssignment></simpleStatement></statement><colon_delim></colon_delim><statements1><statement><simpleStatement><ioStatement><outputStatement><write></write><left_bracket_delim></left_bracket_delim><expression><expression1></expression1><orExpression><orExpression1></orExpression1><andExpression><andExpression1></andExpression1><comparisonExpression><comparisonExpression1><comparisonExpression1><comparisonExpression1></comparisonExpression1><term><term1></term1><factor><constant><int_const attribute="1"></int_const></constant></factor></term><addOperator><plus_op></plus_op></addOperator></comparisonExpression1><term><term1><term1></term1><factor><constant><int_const attribute="3"></int_const></constant></factor><mulOperator><mul_op></mul_op></mulOperator></term1><factor><constant><int_const attribute="2"></int_const></constant></factor></term><addOperator><plus_op></plus_op></addOperator></comparisonExpression1><term><term1></term1><factor><variableOrFuncCall><afterIdentifier></afterIdentifier><identifier attribute="c"></identifier></variableOrFuncCall></factor></term></comparisonExpression></andExpression></orExpression></expression><right_bracket_delim></right_bracket_delim></outputStatement></ioStatement></simpleStatement></statement><colon_delim></colon_delim><statements1></statements1></statements1></statements1></statements1></statements1></statements1></statements1></statements1></statements1></statements1></statements1></statements1></statements1></statements1></statements1></statements1></statements1></statements1></statements1></statements><r_c_bracket_delim></r_c_bracket_delim></block></mainFunction></program>